[{"city": "Corralitos", "distance": "0.0", "altitude": "56.0", "longitude": "-121.786143", "state": "CA", "seg_id": "662017", "latitude": "36.971476"}, {"city": "Corralitos", "distance": "8.2", "altitude": "56.6", "longitude": "-121.786231", "state": "CA", "seg_id": "662017", "latitude": "36.971499"}, {"city": "Corralitos", "distance": "16.4", "altitude": "57.0", "longitude": "-121.786318", "state": "CA", "seg_id": "662017", "latitude": "36.971522"}, {"city": "Corralitos", "distance": "24.6", "altitude": "57.4", "longitude": "-121.786405", "state": "CA", "seg_id": "662017", "latitude": "36.971543"}, {"city": "Corralitos", "distance": "32.7", "altitude": "58.0", "longitude": "-121.78649", "state": "CA", "seg_id": "662017", "latitude": "36.971562"}, {"city": "Corralitos", "distance": "40.7", "altitude": "58.4", "longitude": "-121.786576", "state": "CA", "seg_id": "662017", "latitude": "36.971581"}, {"city": "Corralitos", "distance": "48.6", "altitude": "59.0", "longitude": "-121.786659", "state": "CA", "seg_id": "662017", "latitude": "36.9716"}, {"city": "Corralitos", "distance": "56.3", "altitude": "59.6", "longitude": "-121.786746", "state": "CA", "seg_id": "662017", "latitude": "36.971616"}, {"city": "Corralitos", "distance": "64.0", "altitude": "60.0", "longitude": "-121.786828", "state": "CA", "seg_id": "662017", "latitude": "36.971632"}, {"city": "Corralitos", "distance": "86.2", "altitude": "60.0", "longitude": "-121.787068", "state": "CA", "seg_id": "662017", "latitude": "36.971666"}, {"city": "Corralitos", "distance": "108.0", "altitude": "60.4", "longitude": "-121.787309", "state": "CA", "seg_id": "662017", "latitude": "36.971696"}, {"city": "Corralitos", "distance": "115.2", "altitude": "61.0", "longitude": "-121.787394", "state": "CA", "seg_id": "662017", "latitude": "36.971705"}, {"city": "Corralitos", "distance": "122.2", "altitude": "61.4", "longitude": "-121.787473", "state": "CA", "seg_id": "662017", "latitude": "36.971711"}, {"city": "Corralitos", "distance": "129.3", "altitude": "61.8", "longitude": "-121.787551", "state": "CA", "seg_id": "662017", "latitude": "36.971717"}, {"city": "Corralitos", "distance": "136.4", "altitude": "62.2", "longitude": "-121.787629", "state": "CA", "seg_id": "662017", "latitude": "36.971721"}, {"city": "Corralitos", "distance": "171.0", "altitude": "62.6", "longitude": "-121.788013", "state": "CA", "seg_id": "662017", "latitude": "36.97174"}, {"city": "Corralitos", "distance": "177.8", "altitude": "63.2", "longitude": "-121.788088", "state": "CA", "seg_id": "662017", "latitude": "36.971743"}, {"city": "Corralitos", "distance": "184.5", "altitude": "63.6", "longitude": "-121.788164", "state": "CA", "seg_id": "662017", "latitude": "36.971747"}, {"city": "Corralitos", "distance": "191.2", "altitude": "64.2", "longitude": "-121.788238", "state": "CA", "seg_id": "662017", "latitude": "36.971752"}, {"city": "Corralitos", "distance": "197.8", "altitude": "64.6", "longitude": "-121.788311", "state": "CA", "seg_id": "662017", "latitude": "36.971756"}, {"city": "Corralitos", "distance": "224.4", "altitude": "64.6", "longitude": "-121.788606", "state": "CA", "seg_id": "662017", "latitude": "36.971769"}, {"city": "Corralitos", "distance": "231.0", "altitude": "65.0", "longitude": "-121.788676", "state": "CA", "seg_id": "662017", "latitude": "36.971772"}, {"city": "Corralitos", "distance": "237.2", "altitude": "65.6", "longitude": "-121.788748", "state": "CA", "seg_id": "662017", "latitude": "36.971777"}, {"city": "Corralitos", "distance": "243.7", "altitude": "66.0", "longitude": "-121.788821", "state": "CA", "seg_id": "662017", "latitude": "36.97178"}, {"city": "Corralitos", "distance": "250.0", "altitude": "66.4", "longitude": "-121.788892", "state": "CA", "seg_id": "662017", "latitude": "36.971781"}, {"city": "Corralitos", "distance": "256.6", "altitude": "66.8", "longitude": "-121.788962", "state": "CA", "seg_id": "662017", "latitude": "36.971783"}, {"city": "Corralitos", "distance": "263.0", "altitude": "66.8", "longitude": "-121.789032", "state": "CA", "seg_id": "662017", "latitude": "36.971788"}, {"city": "Corralitos", "distance": "295.6", "altitude": "66.8", "longitude": "-121.78939", "state": "CA", "seg_id": "662017", "latitude": "36.971783"}, {"city": "Corralitos", "distance": "308.1", "altitude": "67.2", "longitude": "-121.789527", "state": "CA", "seg_id": "662017", "latitude": "36.971779"}, {"city": "Corralitos", "distance": "314.1", "altitude": "67.6", "longitude": "-121.789593", "state": "CA", "seg_id": "662017", "latitude": "36.971775"}, {"city": "Corralitos", "distance": "320.1", "altitude": "68.0", "longitude": "-121.78966", "state": "CA", "seg_id": "662017", "latitude": "36.971771"}, {"city": "Corralitos", "distance": "325.9", "altitude": "68.4", "longitude": "-121.789723", "state": "CA", "seg_id": "662017", "latitude": "36.971768"}, {"city": "Corralitos", "distance": "331.6", "altitude": "68.8", "longitude": "-121.789784", "state": "CA", "seg_id": "662017", "latitude": "36.971762"}, {"city": "Corralitos", "distance": "369.2", "altitude": "68.8", "longitude": "-121.790195", "state": "CA", "seg_id": "662017", "latitude": "36.971681"}, {"city": "Corralitos", "distance": "379.4", "altitude": "69.2", "longitude": "-121.790306", "state": "CA", "seg_id": "662017", "latitude": "36.97166"}, {"city": "Corralitos", "distance": "384.6", "altitude": "69.8", "longitude": "-121.790362", "state": "CA", "seg_id": "662017", "latitude": "36.971649"}, {"city": "Corralitos", "distance": "389.9", "altitude": "70.2", "longitude": "-121.790418", "state": "CA", "seg_id": "662017", "latitude": "36.971638"}, {"city": "Corralitos", "distance": "395.3", "altitude": "70.6", "longitude": "-121.790477", "state": "CA", "seg_id": "662017", "latitude": "36.971626"}, {"city": "Corralitos", "distance": "400.8", "altitude": "71.0", "longitude": "-121.790541", "state": "CA", "seg_id": "662017", "latitude": "36.971614"}, {"city": "Corralitos", "distance": "422.0", "altitude": "71.4", "longitude": "-121.790769", "state": "CA", "seg_id": "662017", "latitude": "36.97157"}, {"city": "Corralitos", "distance": "427.1", "altitude": "71.8", "longitude": "-121.790826", "state": "CA", "seg_id": "662017", "latitude": "36.97156"}, {"city": "Corralitos", "distance": "432.4", "altitude": "72.2", "longitude": "-121.790883", "state": "CA", "seg_id": "662017", "latitude": "36.971549"}, {"city": "Corralitos", "distance": "437.7", "altitude": "72.6", "longitude": "-121.790941", "state": "CA", "seg_id": "662017", "latitude": "36.971535"}, {"city": "Corralitos", "distance": "442.9", "altitude": "73.0", "longitude": "-121.791003", "state": "CA", "seg_id": "662017", "latitude": "36.971524"}, {"city": "Corralitos", "distance": "475.2", "altitude": "73.0", "longitude": "-121.791347", "state": "CA", "seg_id": "662017", "latitude": "36.971453"}, {"city": "Corralitos", "distance": "480.5", "altitude": "73.4", "longitude": "-121.791406", "state": "CA", "seg_id": "662017", "latitude": "36.971439"}, {"city": "Corralitos", "distance": "485.9", "altitude": "73.8", "longitude": "-121.791468", "state": "CA", "seg_id": "662017", "latitude": "36.971425"}, {"city": "Corralitos", "distance": "491.3", "altitude": "74.2", "longitude": "-121.791526", "state": "CA", "seg_id": "662017", "latitude": "36.971413"}, {"city": "Corralitos", "distance": "496.6", "altitude": "74.8", "longitude": "-121.791585", "state": "CA", "seg_id": "662017", "latitude": "36.971401"}, {"city": "Corralitos", "distance": "501.8", "altitude": "75.2", "longitude": "-121.791643", "state": "CA", "seg_id": "662017", "latitude": "36.971392"}, {"city": "Corralitos", "distance": "512.5", "altitude": "75.2", "longitude": "-121.79176", "state": "CA", "seg_id": "662017", "latitude": "36.971372"}, {"city": "Corralitos", "distance": "517.9", "altitude": "75.2", "longitude": "-121.791818", "state": "CA", "seg_id": "662017", "latitude": "36.971368"}, {"city": "Corralitos", "distance": "528.9", "altitude": "75.2", "longitude": "-121.791937", "state": "CA", "seg_id": "662017", "latitude": "36.971346"}, {"city": "Corralitos", "distance": "534.4", "altitude": "75.6", "longitude": "-121.791994", "state": "CA", "seg_id": "662017", "latitude": "36.971336"}, {"city": "Corralitos", "distance": "539.8", "altitude": "76.0", "longitude": "-121.792051", "state": "CA", "seg_id": "662017", "latitude": "36.971325"}, {"city": "Corralitos", "distance": "545.1", "altitude": "76.4", "longitude": "-121.79211", "state": "CA", "seg_id": "662017", "latitude": "36.971314"}, {"city": "Corralitos", "distance": "550.4", "altitude": "76.8", "longitude": "-121.792168", "state": "CA", "seg_id": "662017", "latitude": "36.971304"}, {"city": "Corralitos", "distance": "555.7", "altitude": "77.2", "longitude": "-121.792226", "state": "CA", "seg_id": "662017", "latitude": "36.971292"}, {"city": "Corralitos", "distance": "561.0", "altitude": "77.2", "longitude": "-121.792285", "state": "CA", "seg_id": "662017", "latitude": "36.971282"}, {"city": "Corralitos", "distance": "571.6", "altitude": "77.6", "longitude": "-121.792409", "state": "CA", "seg_id": "662017", "latitude": "36.971274"}, {"city": "Corralitos", "distance": "576.9", "altitude": "78.2", "longitude": "-121.792467", "state": "CA", "seg_id": "662017", "latitude": "36.97127"}, {"city": "Corralitos", "distance": "582.2", "altitude": "78.6", "longitude": "-121.792522", "state": "CA", "seg_id": "662017", "latitude": "36.971267"}, {"city": "Corralitos", "distance": "587.3", "altitude": "79.0", "longitude": "-121.792576", "state": "CA", "seg_id": "662017", "latitude": "36.971263"}, {"city": "Corralitos", "distance": "592.5", "altitude": "79.4", "longitude": "-121.792631", "state": "CA", "seg_id": "662017", "latitude": "36.97126"}, {"city": "Corralitos", "distance": "597.6", "altitude": "79.4", "longitude": "-121.792682", "state": "CA", "seg_id": "662017", "latitude": "36.971256"}, {"city": "Corralitos", "distance": "602.7", "altitude": "79.8", "longitude": "-121.792733", "state": "CA", "seg_id": "662017", "latitude": "36.971257"}, {"city": "Corralitos", "distance": "607.7", "altitude": "80.2", "longitude": "-121.79279", "state": "CA", "seg_id": "662017", "latitude": "36.97126"}, {"city": "Corralitos", "distance": "612.6", "altitude": "80.8", "longitude": "-121.792842", "state": "CA", "seg_id": "662017", "latitude": "36.971259"}, {"city": "Corralitos", "distance": "617.6", "altitude": "81.2", "longitude": "-121.792892", "state": "CA", "seg_id": "662017", "latitude": "36.971258"}, {"city": "Corralitos", "distance": "622.6", "altitude": "81.6", "longitude": "-121.792945", "state": "CA", "seg_id": "662017", "latitude": "36.971259"}, {"city": "Corralitos", "distance": "627.5", "altitude": "82.0", "longitude": "-121.793002", "state": "CA", "seg_id": "662017", "latitude": "36.971261"}, {"city": "Corralitos", "distance": "632.3", "altitude": "82.6", "longitude": "-121.79306", "state": "CA", "seg_id": "662017", "latitude": "36.971259"}, {"city": "Corralitos", "distance": "637.1", "altitude": "83.4", "longitude": "-121.793116", "state": "CA", "seg_id": "662017", "latitude": "36.971258"}, {"city": "Corralitos", "distance": "642.0", "altitude": "83.8", "longitude": "-121.793176", "state": "CA", "seg_id": "662017", "latitude": "36.971258"}, {"city": "Corralitos", "distance": "651.9", "altitude": "84.2", "longitude": "-121.793291", "state": "CA", "seg_id": "662017", "latitude": "36.97126"}, {"city": "Corralitos", "distance": "656.9", "altitude": "84.8", "longitude": "-121.793346", "state": "CA", "seg_id": "662017", "latitude": "36.971263"}, {"city": "Corralitos", "distance": "661.8", "altitude": "85.2", "longitude": "-121.793404", "state": "CA", "seg_id": "662017", "latitude": "36.971265"}, {"city": "Corralitos", "distance": "666.6", "altitude": "85.8", "longitude": "-121.79346", "state": "CA", "seg_id": "662017", "latitude": "36.971266"}, {"city": "Corralitos", "distance": "671.4", "altitude": "86.2", "longitude": "-121.793513", "state": "CA", "seg_id": "662017", "latitude": "36.971268"}, {"city": "Corralitos", "distance": "680.9", "altitude": "86.8", "longitude": "-121.793613", "state": "CA", "seg_id": "662017", "latitude": "36.971268"}, {"city": "Corralitos", "distance": "685.1", "altitude": "87.2", "longitude": "-121.793661", "state": "CA", "seg_id": "662017", "latitude": "36.971267"}, {"city": "Corralitos", "distance": "689.4", "altitude": "87.6", "longitude": "-121.793709", "state": "CA", "seg_id": "662017", "latitude": "36.971267"}, {"city": "Corralitos", "distance": "693.8", "altitude": "88.2", "longitude": "-121.793763", "state": "CA", "seg_id": "662017", "latitude": "36.971267"}, {"city": "Corralitos", "distance": "698.5", "altitude": "88.8", "longitude": "-121.79382", "state": "CA", "seg_id": "662017", "latitude": "36.971264"}, {"city": "Corralitos", "distance": "703.7", "altitude": "89.4", "longitude": "-121.793881", "state": "CA", "seg_id": "662017", "latitude": "36.971264"}, {"city": "Corralitos", "distance": "709.2", "altitude": "90.2", "longitude": "-121.793941", "state": "CA", "seg_id": "662017", "latitude": "36.971264"}, {"city": "Corralitos", "distance": "714.7", "altitude": "90.8", "longitude": "-121.794006", "state": "CA", "seg_id": "662017", "latitude": "36.971261"}, {"city": "Corralitos", "distance": "720.1", "altitude": "90.8", "longitude": "-121.794067", "state": "CA", "seg_id": "662017", "latitude": "36.971263"}, {"city": "Corralitos", "distance": "725.3", "altitude": "91.2", "longitude": "-121.794125", "state": "CA", "seg_id": "662017", "latitude": "36.971264"}, {"city": "Corralitos", "distance": "730.7", "altitude": "91.6", "longitude": "-121.794185", "state": "CA", "seg_id": "662017", "latitude": "36.971264"}, {"city": "Corralitos", "distance": "736.2", "altitude": "92.0", "longitude": "-121.794249", "state": "CA", "seg_id": "662017", "latitude": "36.971265"}, {"city": "Corralitos", "distance": "741.7", "altitude": "92.4", "longitude": "-121.794307", "state": "CA", "seg_id": "662017", "latitude": "36.971266"}, {"city": "Corralitos", "distance": "746.8", "altitude": "92.8", "longitude": "-121.794356", "state": "CA", "seg_id": "662017", "latitude": "36.971269"}, {"city": "Corralitos", "distance": "751.4", "altitude": "93.4", "longitude": "-121.794401", "state": "CA", "seg_id": "662017", "latitude": "36.971272"}, {"city": "Corralitos", "distance": "755.8", "altitude": "94.0", "longitude": "-121.794449", "state": "CA", "seg_id": "662017", "latitude": "36.97127"}, {"city": "Corralitos", "distance": "760.0", "altitude": "95.0", "longitude": "-121.794494", "state": "CA", "seg_id": "662017", "latitude": "36.971274"}, {"city": "Corralitos", "distance": "764.3", "altitude": "95.6", "longitude": "-121.794541", "state": "CA", "seg_id": "662017", "latitude": "36.971274"}, {"city": "Corralitos", "distance": "768.5", "altitude": "96.0", "longitude": "-121.794588", "state": "CA", "seg_id": "662017", "latitude": "36.971273"}, {"city": "Corralitos", "distance": "772.6", "altitude": "96.4", "longitude": "-121.794634", "state": "CA", "seg_id": "662017", "latitude": "36.971273"}, {"city": "Corralitos", "distance": "776.8", "altitude": "96.8", "longitude": "-121.79468", "state": "CA", "seg_id": "662017", "latitude": "36.971274"}, {"city": "Corralitos", "distance": "781.0", "altitude": "97.2", "longitude": "-121.794726", "state": "CA", "seg_id": "662017", "latitude": "36.971273"}, {"city": "Corralitos", "distance": "785.1", "altitude": "97.6", "longitude": "-121.794774]", "state": "CA", "seg_id": "662017", "latitude": "36.971272"}]