[{"city": "La Selva Bch", "distance": "0.0", "altitude": "21.8", "longitude": "-121.86023", "state": "CA", "seg_id": "1584083", "latitude": "36.931304"}, {"city": "La Selva Bch", "distance": "17.7", "altitude": "22.9", "longitude": "-121.860056", "state": "CA", "seg_id": "1584083", "latitude": "36.931226"}, {"city": "La Selva Bch", "distance": "35.5", "altitude": "24.8", "longitude": "-121.859879", "state": "CA", "seg_id": "1584083", "latitude": "36.931152"}, {"city": "La Selva Bch", "distance": "52.0", "altitude": "27.0", "longitude": "-121.859716", "state": "CA", "seg_id": "1584083", "latitude": "36.931082"}, {"city": "La Selva Bch", "distance": "67.9", "altitude": "28.0", "longitude": "-121.859553", "state": "CA", "seg_id": "1584083", "latitude": "36.931023"}, {"city": "La Selva Bch", "distance": "83.9", "altitude": "28.6", "longitude": "-121.859394", "state": "CA", "seg_id": "1584083", "latitude": "36.930955"}, {"city": "La Selva Bch", "distance": "99.8", "altitude": "29.0", "longitude": "-121.859234", "state": "CA", "seg_id": "1584083", "latitude": "36.930892"}, {"city": "La Selva Bch", "distance": "116.0", "altitude": "29.4", "longitude": "-121.859068", "state": "CA", "seg_id": "1584083", "latitude": "36.930832"}, {"city": "La Selva Bch", "distance": "132.4", "altitude": "30.2", "longitude": "-121.858897", "state": "CA", "seg_id": "1584083", "latitude": "36.930776"}, {"city": "La Selva Bch", "distance": "149.0", "altitude": "31.4", "longitude": "-121.858724", "state": "CA", "seg_id": "1584083", "latitude": "36.93072"}, {"city": "La Selva Bch", "distance": "166.7", "altitude": "32.2", "longitude": "-121.858551", "state": "CA", "seg_id": "1584083", "latitude": "36.930642"}, {"city": "La Selva Bch", "distance": "184.8", "altitude": "32.4", "longitude": "-121.858371", "state": "CA", "seg_id": "1584083", "latitude": "36.930567"}, {"city": "La Selva Bch", "distance": "200.5", "altitude": "32.5", "longitude": "-121.858214", "state": "CA", "seg_id": "1584083", "latitude": "36.930503"}, {"city": "La Selva Bch", "distance": "215.2", "altitude": "32.8", "longitude": "-121.858066", "state": "CA", "seg_id": "1584083", "latitude": "36.930443"}, {"city": "La Selva Bch", "distance": "234.0", "altitude": "33.0", "longitude": "-121.857872", "state": "CA", "seg_id": "1584083", "latitude": "36.930378"}, {"city": "La Selva Bch", "distance": "250.6", "altitude": "33.2", "longitude": "-121.857694", "state": "CA", "seg_id": "1584083", "latitude": "36.930333"}, {"city": "La Selva Bch", "distance": "268.6", "altitude": "33.0", "longitude": "-121.857529", "state": "CA", "seg_id": "1584083", "latitude": "36.930238"}, {"city": "La Selva Bch", "distance": "285.9", "altitude": "32.7", "longitude": "-121.857356", "state": "CA", "seg_id": "1584083", "latitude": "36.930168"}, {"city": "La Selva Bch", "distance": "304.6", "altitude": "32.7", "longitude": "-121.85716", "state": "CA", "seg_id": "1584083", "latitude": "36.930108"}, {"city": "La Selva Bch", "distance": "322.6", "altitude": "32.7", "longitude": "-121.856973", "state": "CA", "seg_id": "1584083", "latitude": "36.930045"}, {"city": "La Selva Bch", "distance": "339.4", "altitude": "32.9", "longitude": "-121.856802", "state": "CA", "seg_id": "1584083", "latitude": "36.929983"}, {"city": "La Selva Bch", "distance": "356.3", "altitude": "32.9", "longitude": "-121.856628", "state": "CA", "seg_id": "1584083", "latitude": "36.92992"}, {"city": "La Selva Bch", "distance": "373.0", "altitude": "32.9", "longitude": "-121.856464", "state": "CA", "seg_id": "1584083", "latitude": "36.929847"}, {"city": "La Selva Bch", "distance": "390.4", "altitude": "33.0", "longitude": "-121.856298", "state": "CA", "seg_id": "1584083", "latitude": "36.929765"}, {"city": "La Selva Bch", "distance": "407.1", "altitude": "33.0", "longitude": "-121.856131", "state": "CA", "seg_id": "1584083", "latitude": "36.929697"}, {"city": "La Selva Bch", "distance": "425.2", "altitude": "33.0", "longitude": "-121.855949", "state": "CA", "seg_id": "1584083", "latitude": "36.929623"}, {"city": "La Selva Bch", "distance": "442.4", "altitude": "33.0", "longitude": "-121.855778", "state": "CA", "seg_id": "1584083", "latitude": "36.929551"}, {"city": "La Selva Bch", "distance": "460.5", "altitude": "33.0", "longitude": "-121.855597", "state": "CA", "seg_id": "1584083", "latitude": "36.929476"}, {"city": "La Selva Bch", "distance": "478.3", "altitude": "33.0", "longitude": "-121.855416", "state": "CA", "seg_id": "1584083", "latitude": "36.929408"}, {"city": "La Selva Bch", "distance": "497.9", "altitude": "32.9", "longitude": "-121.855217", "state": "CA", "seg_id": "1584083", "latitude": "36.929334"}, {"city": "La Selva Bch", "distance": "515.8", "altitude": "32.9", "longitude": "-121.855034", "state": "CA", "seg_id": "1584083", "latitude": "36.929266"}, {"city": "La Selva Bch", "distance": "533.4", "altitude": "32.8", "longitude": "-121.854856", "state": "CA", "seg_id": "1584083", "latitude": "36.929199"}, {"city": "La Selva Bch", "distance": "553.1", "altitude": "32.7", "longitude": "-121.854654", "state": "CA", "seg_id": "1584083", "latitude": "36.929126"}, {"city": "La Selva Bch", "distance": "573.7", "altitude": "32.6", "longitude": "-121.854453", "state": "CA", "seg_id": "1584083", "latitude": "36.929033"}, {"city": "La Selva Bch", "distance": "595.3", "altitude": "32.2", "longitude": "-121.854241", "state": "CA", "seg_id": "1584083", "latitude": "36.928938"}, {"city": "La Selva Bch", "distance": "615.3", "altitude": "32.0", "longitude": "-121.854038", "state": "CA", "seg_id": "1584083", "latitude": "36.92886"}, {"city": "La Selva Bch", "distance": "635.1", "altitude": "31.9", "longitude": "-121.853836", "state": "CA", "seg_id": "1584083", "latitude": "36.928787"}, {"city": "La Selva Bch", "distance": "654.0", "altitude": "31.9", "longitude": "-121.853643", "state": "CA", "seg_id": "1584083", "latitude": "36.928717"}, {"city": "La Selva Bch", "distance": "671.4", "altitude": "31.9", "longitude": "-121.853474", "state": "CA", "seg_id": "1584083", "latitude": "36.928637"}, {"city": "La Selva Bch", "distance": "690.1", "altitude": "32.0", "longitude": "-121.853285", "state": "CA", "seg_id": "1584083", "latitude": "36.928564"}, {"city": "La Selva Bch", "distance": "707.4", "altitude": "32.3", "longitude": "-121.853107", "state": "CA", "seg_id": "1584083", "latitude": "36.928501"}, {"city": "La Selva Bch", "distance": "724.4", "altitude": "32.6", "longitude": "-121.852934", "state": "CA", "seg_id": "1584083", "latitude": "36.928436"}, {"city": "La Selva Bch", "distance": "742.8", "altitude": "32.9", "longitude": "-121.85275", "state": "CA", "seg_id": "1584083", "latitude": "36.928361"}, {"city": "La Selva Bch", "distance": "760.7", "altitude": "33.4", "longitude": "-121.852568", "state": "CA", "seg_id": "1584083", "latitude": "36.928292"}, {"city": "La Selva Bch", "distance": "776.9", "altitude": "34.8", "longitude": "-121.852404", "state": "CA", "seg_id": "1584083", "latitude": "36.92823"}, {"city": "La Selva Bch", "distance": "793.6", "altitude": "36.9", "longitude": "-121.852235", "state": "CA", "seg_id": "1584083", "latitude": "36.928163"}, {"city": "La Selva Bch", "distance": "809.9", "altitude": "37.6", "longitude": "-121.85207]", "state": "CA", "seg_id": "1584083", "latitude": "36.928101"}]