[{"city": "Gilroy", "distance": "0.0", "altitude": "79.2", "longitude": "-121.644872", "state": "CA", "seg_id": "5987336", "latitude": "37.029641"}, {"city": "Gilroy", "distance": "11.4", "altitude": "79.2", "longitude": "-121.644989", "state": "CA", "seg_id": "5987336", "latitude": "37.029678"}, {"city": "Gilroy", "distance": "22.6", "altitude": "79.2", "longitude": "-121.64511", "state": "CA", "seg_id": "5987336", "latitude": "37.0297"}, {"city": "Gilroy", "distance": "33.6", "altitude": "79.2", "longitude": "-121.645228", "state": "CA", "seg_id": "5987336", "latitude": "37.029713"}, {"city": "Gilroy", "distance": "44.3", "altitude": "79.2", "longitude": "-121.645345", "state": "CA", "seg_id": "5987336", "latitude": "37.02972"}, {"city": "Gilroy", "distance": "54.8", "altitude": "79.6", "longitude": "-121.645468", "state": "CA", "seg_id": "5987336", "latitude": "37.029725"}, {"city": "Gilroy", "distance": "65.4", "altitude": "80.0", "longitude": "-121.645588", "state": "CA", "seg_id": "5987336", "latitude": "37.029728"}, {"city": "Gilroy", "distance": "76.2", "altitude": "80.4", "longitude": "-121.645712", "state": "CA", "seg_id": "5987336", "latitude": "37.029734"}, {"city": "Gilroy", "distance": "87.0", "altitude": "80.8", "longitude": "-121.645835", "state": "CA", "seg_id": "5987336", "latitude": "37.029741"}, {"city": "Gilroy", "distance": "98.0", "altitude": "81.4", "longitude": "-121.645958", "state": "CA", "seg_id": "5987336", "latitude": "37.029749"}, {"city": "Gilroy", "distance": "109.0", "altitude": "81.4", "longitude": "-121.646084", "state": "CA", "seg_id": "5987336", "latitude": "37.029755"}, {"city": "Gilroy", "distance": "120.3", "altitude": "81.4", "longitude": "-121.646212", "state": "CA", "seg_id": "5987336", "latitude": "37.029764"}, {"city": "Gilroy", "distance": "131.5", "altitude": "81.4", "longitude": "-121.646336", "state": "CA", "seg_id": "5987336", "latitude": "37.029774"}, {"city": "Gilroy", "distance": "142.9", "altitude": "81.4", "longitude": "-121.646463", "state": "CA", "seg_id": "5987336", "latitude": "37.029781"}, {"city": "Gilroy", "distance": "154.4", "altitude": "81.4", "longitude": "-121.646588", "state": "CA", "seg_id": "5987336", "latitude": "37.02979"}, {"city": "Gilroy", "distance": "165.8", "altitude": "81.4", "longitude": "-121.64672", "state": "CA", "seg_id": "5987336", "latitude": "37.029801"}, {"city": "Gilroy", "distance": "177.2", "altitude": "81.4", "longitude": "-121.646846", "state": "CA", "seg_id": "5987336", "latitude": "37.029811"}, {"city": "Gilroy", "distance": "188.5", "altitude": "81.4", "longitude": "-121.646977", "state": "CA", "seg_id": "5987336", "latitude": "37.02982"}, {"city": "Gilroy", "distance": "199.7", "altitude": "81.4", "longitude": "-121.647101", "state": "CA", "seg_id": "5987336", "latitude": "37.029829"}, {"city": "Gilroy", "distance": "210.9", "altitude": "81.4", "longitude": "-121.647225", "state": "CA", "seg_id": "5987336", "latitude": "37.029837"}, {"city": "Gilroy", "distance": "221.9", "altitude": "81.8", "longitude": "-121.647347", "state": "CA", "seg_id": "5987336", "latitude": "37.029845"}, {"city": "Gilroy", "distance": "232.8", "altitude": "82.2", "longitude": "-121.64747", "state": "CA", "seg_id": "5987336", "latitude": "37.029853"}, {"city": "Gilroy", "distance": "243.5", "altitude": "82.8", "longitude": "-121.647587", "state": "CA", "seg_id": "5987336", "latitude": "37.029857"}, {"city": "Gilroy", "distance": "254.0", "altitude": "83.2", "longitude": "-121.647702", "state": "CA", "seg_id": "5987336", "latitude": "37.029852"}, {"city": "Gilroy", "distance": "264.4", "altitude": "83.6", "longitude": "-121.64782", "state": "CA", "seg_id": "5987336", "latitude": "37.029841"}, {"city": "Gilroy", "distance": "274.7", "altitude": "83.6", "longitude": "-121.647937", "state": "CA", "seg_id": "5987336", "latitude": "37.029828"}, {"city": "Gilroy", "distance": "285.2", "altitude": "83.6", "longitude": "-121.648053", "state": "CA", "seg_id": "5987336", "latitude": "37.029817"}, {"city": "Gilroy", "distance": "296.1", "altitude": "83.6", "longitude": "-121.648178", "state": "CA", "seg_id": "5987336", "latitude": "37.02981"}, {"city": "Gilroy", "distance": "307.1", "altitude": "83.6", "longitude": "-121.6483", "state": "CA", "seg_id": "5987336", "latitude": "37.029801"}, {"city": "Gilroy", "distance": "318.4", "altitude": "83.6", "longitude": "-121.648429", "state": "CA", "seg_id": "5987336", "latitude": "37.02979"}, {"city": "Gilroy", "distance": "329.7", "altitude": "83.6", "longitude": "-121.648553", "state": "CA", "seg_id": "5987336", "latitude": "37.029778"}, {"city": "Gilroy", "distance": "341.1", "altitude": "83.6", "longitude": "-121.64868", "state": "CA", "seg_id": "5987336", "latitude": "37.029764"}, {"city": "Gilroy", "distance": "352.8", "altitude": "83.6", "longitude": "-121.648815", "state": "CA", "seg_id": "5987336", "latitude": "37.029752"}, {"city": "Gilroy", "distance": "364.6", "altitude": "83.6", "longitude": "-121.648946", "state": "CA", "seg_id": "5987336", "latitude": "37.029741"}, {"city": "Gilroy", "distance": "376.4", "altitude": "83.6", "longitude": "-121.649075", "state": "CA", "seg_id": "5987336", "latitude": "37.029733"}, {"city": "Gilroy", "distance": "388.2", "altitude": "83.6", "longitude": "-121.649206", "state": "CA", "seg_id": "5987336", "latitude": "37.029729"}, {"city": "Gilroy", "distance": "399.8", "altitude": "83.6", "longitude": "-121.649336", "state": "CA", "seg_id": "5987336", "latitude": "37.029728"}, {"city": "Gilroy", "distance": "411.1", "altitude": "83.6", "longitude": "-121.649462", "state": "CA", "seg_id": "5987336", "latitude": "37.029728"}, {"city": "Gilroy", "distance": "422.7", "altitude": "83.6", "longitude": "-121.649597", "state": "CA", "seg_id": "5987336", "latitude": "37.029734"}, {"city": "Gilroy", "distance": "434.3", "altitude": "83.6", "longitude": "-121.649727", "state": "CA", "seg_id": "5987336", "latitude": "37.02974"}, {"city": "Gilroy", "distance": "446.0", "altitude": "83.6", "longitude": "-121.64986", "state": "CA", "seg_id": "5987336", "latitude": "37.029746"}, {"city": "Gilroy", "distance": "457.9", "altitude": "83.6", "longitude": "-121.649991", "state": "CA", "seg_id": "5987336", "latitude": "37.029752"}, {"city": "Gilroy", "distance": "469.8", "altitude": "83.6", "longitude": "-121.650124", "state": "CA", "seg_id": "5987336", "latitude": "37.02976"}, {"city": "Gilroy", "distance": "481.8", "altitude": "83.6", "longitude": "-121.650257", "state": "CA", "seg_id": "5987336", "latitude": "37.029768"}, {"city": "Gilroy", "distance": "493.6", "altitude": "83.6", "longitude": "-121.650387", "state": "CA", "seg_id": "5987336", "latitude": "37.029775"}, {"city": "Gilroy", "distance": "505.3", "altitude": "83.6", "longitude": "-121.650517", "state": "CA", "seg_id": "5987336", "latitude": "37.029781"}, {"city": "Gilroy", "distance": "516.9", "altitude": "83.6", "longitude": "-121.650644", "state": "CA", "seg_id": "5987336", "latitude": "37.029786"}, {"city": "Gilroy", "distance": "528.4", "altitude": "83.6", "longitude": "-121.650773", "state": "CA", "seg_id": "5987336", "latitude": "37.029793"}, {"city": "Gilroy", "distance": "539.9", "altitude": "83.6", "longitude": "-121.650904", "state": "CA", "seg_id": "5987336", "latitude": "37.029804"}, {"city": "Gilroy", "distance": "551.5", "altitude": "83.6", "longitude": "-121.651031", "state": "CA", "seg_id": "5987336", "latitude": "37.02982"}, {"city": "Gilroy", "distance": "563.0", "altitude": "83.6", "longitude": "-121.65116", "state": "CA", "seg_id": "5987336", "latitude": "37.029839"}, {"city": "Gilroy", "distance": "574.5", "altitude": "83.6", "longitude": "-121.651277", "state": "CA", "seg_id": "5987336", "latitude": "37.029863"}, {"city": "Gilroy", "distance": "586.0", "altitude": "83.6", "longitude": "-121.6514", "state": "CA", "seg_id": "5987336", "latitude": "37.029893"}, {"city": "Gilroy", "distance": "597.4", "altitude": "83.6", "longitude": "-121.651517", "state": "CA", "seg_id": "5987336", "latitude": "37.029924"}, {"city": "Gilroy", "distance": "609.0", "altitude": "83.6", "longitude": "-121.651643", "state": "CA", "seg_id": "5987336", "latitude": "37.029955"}, {"city": "Gilroy", "distance": "620.9", "altitude": "83.6", "longitude": "-121.651772", "state": "CA", "seg_id": "5987336", "latitude": "37.029988"}, {"city": "Gilroy", "distance": "633.0", "altitude": "83.6", "longitude": "-121.651903", "state": "CA", "seg_id": "5987336", "latitude": "37.030024"}, {"city": "Gilroy", "distance": "645.5", "altitude": "83.6", "longitude": "-121.652032", "state": "CA", "seg_id": "5987336", "latitude": "37.030059"}, {"city": "Gilroy", "distance": "658.7", "altitude": "83.6", "longitude": "-121.652172", "state": "CA", "seg_id": "5987336", "latitude": "37.030089"}, {"city": "Gilroy", "distance": "672.0", "altitude": "83.6", "longitude": "-121.652317", "state": "CA", "seg_id": "5987336", "latitude": "37.03012"}, {"city": "Gilroy", "distance": "685.5", "altitude": "83.6", "longitude": "-121.652453", "state": "CA", "seg_id": "5987336", "latitude": "37.030147"}, {"city": "Gilroy", "distance": "698.4", "altitude": "83.6", "longitude": "-121.652592", "state": "CA", "seg_id": "5987336", "latitude": "37.03016"}, {"city": "Gilroy", "distance": "710.9", "altitude": "83.6", "longitude": "-121.652724", "state": "CA", "seg_id": "5987336", "latitude": "37.030162"}, {"city": "Gilroy", "distance": "722.6", "altitude": "83.6", "longitude": "-121.652856", "state": "CA", "seg_id": "5987336", "latitude": "37.030155"}, {"city": "Gilroy", "distance": "734.4", "altitude": "83.6", "longitude": "-121.65298", "state": "CA", "seg_id": "5987336", "latitude": "37.030146"}, {"city": "Gilroy", "distance": "745.9", "altitude": "83.6", "longitude": "-121.653108", "state": "CA", "seg_id": "5987336", "latitude": "37.030138"}, {"city": "Gilroy", "distance": "757.5", "altitude": "83.6", "longitude": "-121.653237", "state": "CA", "seg_id": "5987336", "latitude": "37.030129"}, {"city": "Gilroy", "distance": "769.2", "altitude": "83.6", "longitude": "-121.65337", "state": "CA", "seg_id": "5987336", "latitude": "37.030122"}, {"city": "Gilroy", "distance": "780.9", "altitude": "83.6", "longitude": "-121.653511", "state": "CA", "seg_id": "5987336", "latitude": "37.030115"}, {"city": "Gilroy", "distance": "793.0", "altitude": "83.6", "longitude": "-121.653646", "state": "CA", "seg_id": "5987336", "latitude": "37.030106"}, {"city": "Gilroy", "distance": "805.2", "altitude": "83.6", "longitude": "-121.653784", "state": "CA", "seg_id": "5987336", "latitude": "37.030097"}, {"city": "Gilroy", "distance": "817.7", "altitude": "83.6", "longitude": "-121.653921", "state": "CA", "seg_id": "5987336", "latitude": "37.030087"}, {"city": "Gilroy", "distance": "830.3", "altitude": "83.6", "longitude": "-121.654057", "state": "CA", "seg_id": "5987336", "latitude": "37.030076"}, {"city": "Gilroy", "distance": "842.8", "altitude": "83.6", "longitude": "-121.654196", "state": "CA", "seg_id": "5987336", "latitude": "37.030063"}, {"city": "Gilroy", "distance": "855.1", "altitude": "83.2", "longitude": "-121.654328", "state": "CA", "seg_id": "5987336", "latitude": "37.030051"}, {"city": "Gilroy", "distance": "867.0", "altitude": "82.6", "longitude": "-121.654459", "state": "CA", "seg_id": "5987336", "latitude": "37.030042"}, {"city": "Gilroy", "distance": "878.7", "altitude": "82.2", "longitude": "-121.654592", "state": "CA", "seg_id": "5987336", "latitude": "37.030035"}, {"city": "Gilroy", "distance": "890.3", "altitude": "81.6", "longitude": "-121.654725", "state": "CA", "seg_id": "5987336", "latitude": "37.03003"}, {"city": "Gilroy", "distance": "902.0", "altitude": "81.2", "longitude": "-121.654854", "state": "CA", "seg_id": "5987336", "latitude": "37.030025"}, {"city": "Gilroy", "distance": "913.8", "altitude": "81.2", "longitude": "-121.654988]", "state": "CA", "seg_id": "5987336", "latitude": "37.030017"}]